README
setup.py
jdcloud_cli/__init__.py
jdcloud_cli/client_factory.py
jdcloud_cli/config.py
jdcloud_cli/const.py
jdcloud_cli/inputjson_parser.py
jdcloud_cli/jdc.py
jdcloud_cli/logger.py
jdcloud_cli/parameter_builder.py
jdcloud_cli/printer.py
jdcloud_cli/skeleton.py
jdcloud_cli/utils.py
jdcloud_cli/version.py
jdcloud_cli.egg-info/PKG-INFO
jdcloud_cli.egg-info/SOURCES.txt
jdcloud_cli.egg-info/dependency_links.txt
jdcloud_cli.egg-info/entry_points.txt
jdcloud_cli.egg-info/requires.txt
jdcloud_cli.egg-info/top_level.txt
jdcloud_cli/cement/__init__.py
jdcloud_cli/cement/core/__init__.py
jdcloud_cli/cement/core/arg.py
jdcloud_cli/cement/core/backend.py
jdcloud_cli/cement/core/cache.py
jdcloud_cli/cement/core/config.py
jdcloud_cli/cement/core/controller.py
jdcloud_cli/cement/core/exc.py
jdcloud_cli/cement/core/extension.py
jdcloud_cli/cement/core/foundation.py
jdcloud_cli/cement/core/handler.py
jdcloud_cli/cement/core/hook.py
jdcloud_cli/cement/core/interface.py
jdcloud_cli/cement/core/log.py
jdcloud_cli/cement/core/mail.py
jdcloud_cli/cement/core/meta.py
jdcloud_cli/cement/core/output.py
jdcloud_cli/cement/core/plugin.py
jdcloud_cli/cement/ext/__init__.py
jdcloud_cli/cement/ext/ext_alarm.py
jdcloud_cli/cement/ext/ext_argcomplete.py
jdcloud_cli/cement/ext/ext_argparse.py
jdcloud_cli/cement/ext/ext_colorlog.py
jdcloud_cli/cement/ext/ext_configobj.py
jdcloud_cli/cement/ext/ext_configparser.py
jdcloud_cli/cement/ext/ext_daemon.py
jdcloud_cli/cement/ext/ext_dummy.py
jdcloud_cli/cement/ext/ext_genshi.py
jdcloud_cli/cement/ext/ext_handlebars.py
jdcloud_cli/cement/ext/ext_jinja2.py
jdcloud_cli/cement/ext/ext_json.py
jdcloud_cli/cement/ext/ext_json_configobj.py
jdcloud_cli/cement/ext/ext_logging.py
jdcloud_cli/cement/ext/ext_memcached.py
jdcloud_cli/cement/ext/ext_mustache.py
jdcloud_cli/cement/ext/ext_plugin.py
jdcloud_cli/cement/ext/ext_redis.py
jdcloud_cli/cement/ext/ext_reload_config.py
jdcloud_cli/cement/ext/ext_smtp.py
jdcloud_cli/cement/ext/ext_tabulate.py
jdcloud_cli/cement/ext/ext_watchdog.py
jdcloud_cli/cement/ext/ext_yaml.py
jdcloud_cli/cement/ext/ext_yaml_configobj.py
jdcloud_cli/cement/utils/__init__.py
jdcloud_cli/cement/utils/fs.py
jdcloud_cli/cement/utils/misc.py
