Metadata-Version: 1.0
Name: jdcloud-cli
Version: 1.2.12
Summary: Universal Command Line Environment for jdcloud
Home-page: https://github.com/jdcloud-api/jdcloud-cli
Author: JDCloud API Gateway Team
Author-email: UNKNOWN
License: UNKNOWN
Platform: unix
Platform: linux
Platform: osx
Platform: win64
